telemc/__init__.py
telemc/controller.py
telemc/recorder.py
telemc/telemc.py
tests/__init__.py
tests/testutil.py
tests/telemc/__init__.py
tests/telemc/test_recorder.py
symmetry_py_telemc-0.2.0.dist-info/METADATA
symmetry_py_telemc-0.2.0.dist-info/WHEEL
symmetry_py_telemc-0.2.0.dist-info/top_level.txt
symmetry_py_telemc-0.2.0.dist-info/RECORD
